{
    "id": "main-menu",
    "controller": "MainMenuController",

    "children": [
        {
            "id": "version-number",
            "component": "UILabel",
            "style": {
                "text": "Pre Alpha",
                "position": [0, 230],
                "horizontalAlign": "center",
                "verticalAlign": "top",
                "textShadow": true
            }
        },

        {
            "id": "terasology-logo",
            "component": "UIImage",
            "styleClass": "defaultButtonStyle",
            "style": {
                "image": "engine:terasology",
                "size": [512, 128],
                "position": [0, 128],
                "horizontalAlign": "center"
            }
        },

        {
            "id": "settings-button",
            "component": "UIButton",
            "styleClass": "defaultButtonStyle",
            "style": {
                "text": "Settings",
                "position": [0, 460]
            }
        },

        {
            "id": "singleplayer-button",
            "component": "UIButton",
            "styleClass": "defaultButtonStyle",
            "style": {
                "text": "Single player",
                "position": [0, 340]
            }
        },

        {
            "id": "hostgame-button",
            "component": "UIButton",
            "styleClass": "defaultButtonStyle",
            "style": {
                "text": "Host game",
                "position": [0, 380]
            }
        },

        {
            "id": "joingame-button",
            "component": "UIButton",
            "styleClass": "defaultButtonStyle",
            "style": {
                "text": "Join game",
                "position": [0, 420]
            }
        },

        {
            "id": "exit-button",
            "component": "UIButton",
            "styleClass": "defaultButtonStyle",
            "style": {
                "text": "Exit Terasology",
                "position": [0, 540]
            }
        }
    ],

    "style": {
        "backgroundImage": "engine:menubackground"
    }
}